markitdown_office_extension/__init__.py
markitdown_office_extension/docx_converter.py
markitdown_office_extension/epub_converter.py
markitdown_office_extension/html_converter.py
markitdown_office_extension/markdown_converter.py
markitdown_office_extension/patch.py
markitdown_office_extension/pptx_converter.py
markitdown_office_extension/xlsx_converter.py
markitdown_office_extension-0.1.2.dist-info/METADATA
markitdown_office_extension-0.1.2.dist-info/WHEEL
markitdown_office_extension-0.1.2.dist-info/entry_points.txt
markitdown_office_extension-0.1.2.dist-info/licenses/LICENSE
markitdown_office_extension-0.1.2.dist-info/RECORD
