Metadata-Version: 2.4
Name: markitdown-office-extension
Version: 0.1.2
Summary: A markitdown plugin use to customize markdownify
Project-URL: Homepage, https://github.com/qzwxsaedc/markitdown-office-extension
Project-URL: Repository, https://github.com/qzwxsaedc/markitdown-office-extension
Project-URL: Issues, https://github.com/qzwxsaedc/markitdown-office-extension/issues
Author-email: qzwxsaedc <me@qzwxsaedc.com>
License-Expression: MIT
License-File: LICENSE
Keywords: markdown,markitdown,plugin
Classifier: Development Status :: 4 - Beta
Classifier: Programming Language :: Python
Classifier: Programming Language :: Python :: 3.10
Classifier: Programming Language :: Python :: 3.11
Classifier: Programming Language :: Python :: 3.12
Classifier: Programming Language :: Python :: 3.13
Classifier: Programming Language :: Python :: Implementation :: CPython
Classifier: Programming Language :: Python :: Implementation :: PyPy
Requires-Python: >=3.10
